datasette_sqlite_trace.py
datasette_sqlite_trace-0.1.dist-info/METADATA
datasette_sqlite_trace-0.1.dist-info/WHEEL
datasette_sqlite_trace-0.1.dist-info/entry_points.txt
datasette_sqlite_trace-0.1.dist-info/top_level.txt
datasette_sqlite_trace-0.1.dist-info/RECORD
