Metadata-Version: 2.1
Name: datasette-sqlite-trace
Version: 0.1
Summary: Datasette plugin that prints all executed SQL to stderr
Author: Simon Willison
License: Apache-2.0
Project-URL: Homepage, https://github.com/datasette/datasette-sqlite-trace
Project-URL: Changelog, https://github.com/datasette/datasette-sqlite-trace/releases
Project-URL: Issues, https://github.com/datasette/datasette-sqlite-trace/issues
Project-URL: CI, https://github.com/datasette/datasette-sqlite-trace/actions
Classifier: License :: OSI Approved :: Apache Software License
Classifier: Framework :: Datasette
Requires-Dist: datasette
Provides-Extra: test
Requires-Dist: pytest ; extra == 'test'
Requires-Dist: pytest-asyncio ; extra == 'test'
